[
null,
{"id":1,"expanded":true,"name":"MAP001","order":1,"parentId":0,"scrollX":1228.5,"scrollY":691.5},
{"id":2,"expanded":false,"name":"Market","order":3,"parentId":1,"scrollX":1228.5,"scrollY":691.5},
{"id":3,"expanded":true,"name":"Market 2","order":4,"parentId":1,"scrollX":1228.5,"scrollY":691.5},
{"id":4,"expanded":false,"name":"Mountain Village","order":5,"parentId":1,"scrollX":1216.5,"scrollY":1420.5},
{"id":5,"expanded":false,"name":"Fishing Village","order":2,"parentId":1,"scrollX":1081.3333333333333,"scrollY":614.6666666666666}
]